httpfind/__init__.py
httpfind/httpfind.py
httpfind-1.0.1.dist-info/DESCRIPTION.rst
httpfind-1.0.1.dist-info/METADATA
httpfind-1.0.1.dist-info/RECORD
httpfind-1.0.1.dist-info/WHEEL
httpfind-1.0.1.dist-info/entry_points.txt
httpfind-1.0.1.dist-info/metadata.json
httpfind-1.0.1.dist-info/top_level.txt
