Metadata-Version: 2.0
Name: httpfind
Version: 1.0.1
Summary: Search network for HTTP servers using a regular expression filter
Home-page: https://github.com/Overboard/httpfind
Author: Overboard
Author-email: amwroute-git@yahoo.com
License: MIT
Keywords: http find scan filter
Platform: UNKNOWN
Classifier: Development Status :: 4 - Beta
Classifier: Intended Audience :: Developers
Classifier: License :: OSI Approved :: MIT License
Classifier: Programming Language :: Python :: 3
Classifier: Programming Language :: Python :: 3.6
Requires-Dist: aiohttp
